setup.cfg
setup.py
pyf/__init__.py
pyf.components.adapters.standardtools.egg-info/PKG-INFO
pyf.components.adapters.standardtools.egg-info/SOURCES.txt
pyf.components.adapters.standardtools.egg-info/dependency_links.txt
pyf.components.adapters.standardtools.egg-info/entry_points.txt
pyf.components.adapters.standardtools.egg-info/namespace_packages.txt
pyf.components.adapters.standardtools.egg-info/requires.txt
pyf.components.adapters.standardtools.egg-info/top_level.txt
pyf.components.adapters.standardtools.egg-info/zip-safe
pyf/components/__init__.py
pyf/components/adapters/__init__.py
pyf/components/adapters/standardtools/__init__.py
pyf/components/adapters/standardtools/adapter.py
pyf/components/adapters/standardtools/summarize.py
pyf/components/adapters/standardtools/transport.py
pyf/components/adapters/standardtools/tests/__init__.py
pyf/components/adapters/standardtools/tests/test_transport.py