Metadata-Version: 1.0
Name: pyf.components.adapters.standardtools
Version: 1.0.2
Summary: PyF Standard Adapters (standard library)
Home-page: http://www.pyfproject.org/
Author: htaieb, Jonathan Schemoul
Author-email: he.taieb@gmail.com, jonathan.schemoul@gmail.com
License: MIT or PSF
Platform: UNKNOWN
Classifier: Development Status :: 3 - Alpha
Classifier: Operating System :: OS Independent
Classifier: Programming Language :: Python
Classifier: License :: OSI Approved :: MIT License
Classifier: Topic :: Software Development :: Libraries :: Python Modules
